{
	"item": [
		{
			"name": "🏢 Companies",
			"item": [
				{
					"name": "Create Company",
					"event": [
						{
							"listen": "test",
							"script": {
								"exec": [
									"if (pm.response.code === 200 || pm.response.code === 201) {",
									"    const response = pm.response.json();",
									"    if (response.company && response.company.id) {",
									"        pm.collectionVariables.set('companyId', response.company.id);",
									"        console.log('Company ID set:', response.company.id);",
									"    }",
									"}"
								],
								"type": "text/javascript"
							}
						}
					],
					"request": {
						"method": "POST",
						"header": [
							{
								"key": "Content-Type",
								"value": "application/json"
							}
						],
						"body": {
							"mode": "raw",
							"raw": "{\n    \"symbol\": \"AAPL\",\n    \"name\": \"Apple Inc.\",\n    \"market_cap\": 3000000,\n    \"sector\": \"Technology\"\n}"
						},
						"url": {
							"raw": "{{baseUrl}}/api/v1/companies/",
							"host": ["{{baseUrl}}"],
							"path": ["api", "v1", "companies", ""]
						}
					}
				},
				{
					"name": "List Companies",
					"request": {
						"method": "GET",
						"header": [],
						"url": {
							"raw": "{{baseUrl}}/api/v1/companies/?page=1&size=10",
							"host": ["{{baseUrl}}"],
							"path": ["api", "v1", "companies", ""],
							"query": [
								{
									"key": "page",
									"value": "1"
								},
								{
									"key": "size",
									"value": "10"
								}
							]
						}
					}
				},
				{
					"name": "Get Company by Symbol",
					"request": {
						"method": "GET",
						"header": [],
						"url": {
							"raw": "{{baseUrl}}/api/v1/companies/AAPL",
							"host": ["{{baseUrl}}"],
							"path": ["api", "v1", "companies", "AAPL"]
						}
					}
				},
				{
					"name": "Search Companies",
					"request": {
						"method": "GET",
						"header": [],
						"url": {
							"raw": "{{baseUrl}}/api/v1/companies/search?symbol=AAPL&sector=Technology",
							"host": ["{{baseUrl}}"],
							"path": ["api", "v1", "companies", "search"],
							"query": [
								{
									"key": "symbol",
									"value": "AAPL"
								},
								{
									"key": "sector",
									"value": "Technology"
								}
							]
						}
					}
				}
			]
		},
		{
			"name": "📊 Annual Predictions",
			"item": [
				{
					"name": "Create Annual Prediction",
					"event": [
						{
							"listen": "test",
							"script": {
								"exec": [
									"if (pm.response.code === 200 || pm.response.code === 201) {",
									"    const response = pm.response.json();",
									"    if (response.prediction && response.prediction.id) {",
									"        pm.collectionVariables.set('predictionId', response.prediction.id);",
									"        console.log('Prediction ID set:', response.prediction.id);",
									"    }",
									"}"
								],
								"type": "text/javascript"
							}
						}
					],
					"request": {
						"method": "POST",
						"header": [
							{
								"key": "Content-Type",
								"value": "application/json"
							}
						],
						"body": {
							"mode": "raw",
							"raw": "{\n    \"company_symbol\": \"AAPL\",\n    \"company_name\": \"Apple Inc.\",\n    \"market_cap\": 3000000,\n    \"sector\": \"Technology\",\n    \"reporting_year\": \"2024\",\n    \"reporting_quarter\": \"Q1\",\n    \"long_term_debt_to_total_capital\": 0.25,\n    \"total_debt_to_ebitda\": 1.8,\n    \"net_income_margin\": 0.15,\n    \"ebit_to_interest_expense\": 12.5,\n    \"return_on_assets\": 0.18\n}"
						},
						"url": {
							"raw": "{{baseUrl}}/api/v1/predictions/annual",
							"host": ["{{baseUrl}}"],
							"path": ["api", "v1", "predictions", "annual"]
						}
					}
				},
				{
					"name": "Get Annual Predictions",
					"request": {
						"method": "GET",
						"header": [],
						"url": {
							"raw": "{{baseUrl}}/api/v1/predictions/annual?page=1&size=10",
							"host": ["{{baseUrl}}"],
							"path": ["api", "v1", "predictions", "annual"],
							"query": [
								{
									"key": "page",
									"value": "1"
								},
								{
									"key": "size",
									"value": "10"
								}
							]
						}
					}
				},
				{
					"name": "Get Annual Predictions with Filters",
					"request": {
						"method": "GET",
						"header": [],
						"url": {
							"raw": "{{baseUrl}}/api/v1/predictions/annual?company_symbol=AAPL&reporting_year=2024&page=1&size=10",
							"host": ["{{baseUrl}}"],
							"path": ["api", "v1", "predictions", "annual"],
							"query": [
								{
									"key": "company_symbol",
									"value": "AAPL"
								},
								{
									"key": "reporting_year",
									"value": "2024"
								},
								{
									"key": "page",
									"value": "1"
								},
								{
									"key": "size",
									"value": "10"
								}
							]
						}
					}
				},
				{
					"name": "Update Annual Prediction",
					"request": {
						"method": "PUT",
						"header": [
							{
								"key": "Content-Type",
								"value": "application/json"
							}
						],
						"body": {
							"mode": "raw",
							"raw": "{\n    \"company_symbol\": \"AAPL\",\n    \"company_name\": \"Apple Inc. - Updated\",\n    \"market_cap\": 3100000,\n    \"sector\": \"Technology\",\n    \"reporting_year\": \"2024\",\n    \"reporting_quarter\": \"Q1\",\n    \"long_term_debt_to_total_capital\": 0.26,\n    \"total_debt_to_ebitda\": 1.9,\n    \"net_income_margin\": 0.16,\n    \"ebit_to_interest_expense\": 13.0,\n    \"return_on_assets\": 0.19\n}"
						},
						"url": {
							"raw": "{{baseUrl}}/api/v1/predictions/annual/{{predictionId}}",
							"host": ["{{baseUrl}}"],
							"path": ["api", "v1", "predictions", "annual", "{{predictionId}}"]
						}
					}
				},
				{
					"name": "Delete Annual Prediction",
					"request": {
						"method": "DELETE",
						"header": [],
						"url": {
							"raw": "{{baseUrl}}/api/v1/predictions/annual/{{predictionId}}",
							"host": ["{{baseUrl}}"],
							"path": ["api", "v1", "predictions", "annual", "{{predictionId}}"]
						}
					}
				},
				{
					"name": "Bulk Upload Annual (Async)",
					"event": [
						{
							"listen": "test",
							"script": {
								"exec": [
									"if (pm.response.code === 200 || pm.response.code === 201) {",
									"    const response = pm.response.json();",
									"    if (response.job_id) {",
									"        pm.collectionVariables.set('jobId', response.job_id);",
									"        console.log('Job ID set:', response.job_id);",
									"    }",
									"}"
								],
								"type": "text/javascript"
							}
						}
					],
					"request": {
						"method": "POST",
						"header": [],
						"body": {
							"mode": "formdata",
							"formdata": [
								{
									"key": "file",
									"type": "file",
									"src": "/path/to/annual_predictions.csv"
								}
							]
						},
						"url": {
							"raw": "{{baseUrl}}/api/v1/predictions/annual/bulk-upload-async",
							"host": ["{{baseUrl}}"],
							"path": ["api", "v1", "predictions", "annual", "bulk-upload-async"]
						}
					}
				}
			]
		},
		{
			"name": "📈 Quarterly Predictions",
			"item": [
				{
					"name": "Create Quarterly Prediction",
					"request": {
						"method": "POST",
						"header": [
							{
								"key": "Content-Type",
								"value": "application/json"
							}
						],
						"body": {
							"mode": "raw",
							"raw": "{\n    \"company_symbol\": \"MSFT\",\n    \"company_name\": \"Microsoft Corporation\",\n    \"market_cap\": 2800000,\n    \"sector\": \"Technology\",\n    \"reporting_year\": \"2024\",\n    \"reporting_quarter\": \"Q1\",\n    \"total_debt_to_ebitda\": 1.5,\n    \"sga_margin\": 0.22,\n    \"long_term_debt_to_total_capital\": 0.20,\n    \"return_on_capital\": 0.25\n}"
						},
						"url": {
							"raw": "{{baseUrl}}/api/v1/predictions/quarterly",
							"host": ["{{baseUrl}}"],
							"path": ["api", "v1", "predictions", "quarterly"]
						}
					}
				},
				{
					"name": "Get Quarterly Predictions",
					"request": {
						"method": "GET",
						"header": [],
						"url": {
							"raw": "{{baseUrl}}/api/v1/predictions/quarterly?page=1&size=10",
							"host": ["{{baseUrl}}"],
							"path": ["api", "v1", "predictions", "quarterly"],
							"query": [
								{
									"key": "page",
									"value": "1"
								},
								{
									"key": "size",
									"value": "10"
								}
							]
						}
					}
				},
				{
					"name": "Get Quarterly Predictions with Filters",
					"request": {
						"method": "GET",
						"header": [],
						"url": {
							"raw": "{{baseUrl}}/api/v1/predictions/quarterly?company_symbol=MSFT&reporting_year=2024&reporting_quarter=Q1&page=1&size=10",
							"host": ["{{baseUrl}}"],
							"path": ["api", "v1", "predictions", "quarterly"],
							"query": [
								{
									"key": "company_symbol",
									"value": "MSFT"
								},
								{
									"key": "reporting_year",
									"value": "2024"
								},
								{
									"key": "reporting_quarter",
									"value": "Q1"
								},
								{
									"key": "page",
									"value": "1"
								},
								{
									"key": "size",
									"value": "10"
								}
							]
						}
					}
				},
				{
					"name": "Update Quarterly Prediction",
					"request": {
						"method": "PUT",
						"header": [
							{
								"key": "Content-Type",
								"value": "application/json"
							}
						],
						"body": {
							"mode": "raw",
							"raw": "{\n    \"company_symbol\": \"MSFT\",\n    \"company_name\": \"Microsoft Corporation - Updated\",\n    \"market_cap\": 2900000,\n    \"sector\": \"Technology\",\n    \"reporting_year\": \"2024\",\n    \"reporting_quarter\": \"Q1\",\n    \"total_debt_to_ebitda\": 1.6,\n    \"sga_margin\": 0.23,\n    \"long_term_debt_to_total_capital\": 0.21,\n    \"return_on_capital\": 0.26\n}"
						},
						"url": {
							"raw": "{{baseUrl}}/api/v1/predictions/quarterly/{{predictionId}}",
							"host": ["{{baseUrl}}"],
							"path": ["api", "v1", "predictions", "quarterly", "{{predictionId}}"]
						}
					}
				},
				{
					"name": "Delete Quarterly Prediction",
					"request": {
						"method": "DELETE",
						"header": [],
						"url": {
							"raw": "{{baseUrl}}/api/v1/predictions/quarterly/{{predictionId}}",
							"host": ["{{baseUrl}}"],
							"path": ["api", "v1", "predictions", "quarterly", "{{predictionId}}"]
						}
					}
				},
				{
					"name": "Bulk Upload Quarterly (Async)",
					"request": {
						"method": "POST",
						"header": [],
						"body": {
							"mode": "formdata",
							"formdata": [
								{
									"key": "file",
									"type": "file",
									"src": "/path/to/quarterly_predictions.csv"
								}
							]
						},
						"url": {
							"raw": "{{baseUrl}}/api/v1/predictions/quarterly/bulk-upload-async",
							"host": ["{{baseUrl}}"],
							"path": ["api", "v1", "predictions", "quarterly", "bulk-upload-async"]
						}
					}
				}
			]
		},
		{
			"name": "🔄 Job Management",
			"item": [
				{
					"name": "Get Job Status",
					"request": {
						"method": "GET",
						"header": [],
						"url": {
							"raw": "{{baseUrl}}/api/v1/predictions/jobs/{{jobId}}/status",
							"host": ["{{baseUrl}}"],
							"path": ["api", "v1", "predictions", "jobs", "{{jobId}}", "status"]
						}
					}
				},
				{
					"name": "List All Jobs",
					"request": {
						"method": "GET",
						"header": [],
						"url": {
							"raw": "{{baseUrl}}/api/v1/predictions/jobs?limit=50&offset=0",
							"host": ["{{baseUrl}}"],
							"path": ["api", "v1", "predictions", "jobs"],
							"query": [
								{
									"key": "limit",
									"value": "50"
								},
								{
									"key": "offset",
									"value": "0"
								}
							]
						}
					}
				},
				{
					"name": "List Jobs by Status",
					"request": {
						"method": "GET",
						"header": [],
						"url": {
							"raw": "{{baseUrl}}/api/v1/predictions/jobs?status=completed&limit=50&offset=0",
							"host": ["{{baseUrl}}"],
							"path": ["api", "v1", "predictions", "jobs"],
							"query": [
								{
									"key": "status",
									"value": "completed"
								},
								{
									"key": "limit",
									"value": "50"
								},
								{
									"key": "offset",
									"value": "0"
								}
							]
						}
					}
				}
			]
		},
		{
			"name": "📊 Legacy Bulk Upload",
			"item": [
				{
					"name": "Bulk Upload (Synchronous)",
					"request": {
						"method": "POST",
						"header": [],
						"body": {
							"mode": "formdata",
							"formdata": [
								{
									"key": "file",
									"type": "file",
									"src": "/path/to/predictions.csv"
								},
								{
									"key": "prediction_type",
									"value": "annual",
									"type": "text"
								}
							]
						},
						"url": {
							"raw": "{{baseUrl}}/api/v1/predictions/bulk-upload",
							"host": ["{{baseUrl}}"],
							"path": ["api", "v1", "predictions", "bulk-upload"]
						}
					}
				}
			]
		}
	]
}
